seoul256_jupyterlab_theme/__init__.py
seoul256_jupyterlab_theme/_version.py
seoul256_jupyterlab_theme-0.2.0.data/data/share/jupyter/labextensions/seoul256-jupyterlab-theme/package.json
seoul256_jupyterlab_theme-0.2.0.data/data/share/jupyter/labextensions/seoul256-jupyterlab-theme/static/568.8626ba9b2a05ed2f8a88.js
seoul256_jupyterlab_theme-0.2.0.data/data/share/jupyter/labextensions/seoul256-jupyterlab-theme/static/remoteEntry.2bd21849baf1c7c34b32.js
seoul256_jupyterlab_theme-0.2.0.data/data/share/jupyter/labextensions/seoul256-jupyterlab-theme/static/style.js
seoul256_jupyterlab_theme-0.2.0.data/data/share/jupyter/labextensions/seoul256-jupyterlab-theme/static/third-party-licenses.json
seoul256_jupyterlab_theme-0.2.0.data/data/share/jupyter/labextensions/seoul256-jupyterlab-theme/themes/seoul256-jupyterlab-theme/index.css
seoul256_jupyterlab_theme-0.2.0.data/data/share/jupyter/labextensions/seoul256-jupyterlab-theme/themes/seoul256-jupyterlab-theme/index.js
seoul256_jupyterlab_theme-0.2.0.data/data/share/jupyter/labextensions/seoul256-jupyterlab-theme/install.json
seoul256_jupyterlab_theme-0.2.0.dist-info/METADATA
seoul256_jupyterlab_theme-0.2.0.dist-info/WHEEL
seoul256_jupyterlab_theme-0.2.0.dist-info/licenses/LICENSE
seoul256_jupyterlab_theme-0.2.0.dist-info/RECORD
