Metadata-Version: 2.1
Name: seoul256_jupyterlab_theme
Version: 0.2.0
Summary: A JupyterLab theme with Seoul 256 color scheme
Project-URL: Homepage, https://github.com/muwizayeon/seoul256-jupyterlab-theme
Project-URL: Bug Tracker, https://github.com/muwizayeon/seoul256-jupyterlab-theme/issues
Project-URL: Repository, https://github.com/muwizayeon/seoul256-jupyterlab-theme.git
Author-email: muwizayeon <muwizayeon@gmail.com>
License: BSD 3-Clause License
License-File: LICENSE
Classifier: Framework :: Jupyter
Classifier: Framework :: Jupyter :: JupyterLab
Classifier: Framework :: Jupyter :: JupyterLab :: 4
Classifier: Framework :: Jupyter :: JupyterLab :: Extensions
Classifier: Framework :: Jupyter :: JupyterLab :: Extensions :: Prebuilt
Classifier: License :: OSI Approved :: BSD License
Classifier: Programming Language :: Python
Classifier: Programming Language :: Python :: 3
Classifier: Programming Language :: Python :: 3.8
Classifier: Programming Language :: Python :: 3.9
Classifier: Programming Language :: Python :: 3.10
Classifier: Programming Language :: Python :: 3.11
Requires-Python: >=3.8
